watson/__init__.py
watson/mail/__init__.py
watson/mail/messages.py
watson/mail/backends/__init__.py
watson/mail/backends/abc.py
watson/mail/backends/sendmail.py
watson/mail/backends/smtp.py
watson_mail-1.3.1.dist-info/AUTHORS
watson_mail-1.3.1.dist-info/LICENSE
watson_mail-1.3.1.dist-info/METADATA
watson_mail-1.3.1.dist-info/WHEEL
watson_mail-1.3.1.dist-info/top_level.txt
watson_mail-1.3.1.dist-info/RECORD
