Metadata-Version: 2.1
Name: watson-mail
Version: 1.3.1
Summary: Easily compose and send email via sendmail or smtp.
Home-page: http://github.com/watsonpy/watson-mail
Author: Simon Coulton
Author-email: simon@bespohk.com
License: Copyright (c) Bespohk and individual contributors.
Requires-Dist: watson-common (>=1.4.2)
Provides-Extra: test
Requires-Dist: pytest ; extra == 'test'
Requires-Dist: pytest-cov ; extra == 'test'
Requires-Dist: coverage ; extra == 'test'
Requires-Dist: coveralls ; extra == 'test'
